reqgen/__init__.py
reqgen/reqgen.py
reqgen-0.0.11.dist-info/AUTHORS.rst
reqgen-0.0.11.dist-info/LICENSE
reqgen-0.0.11.dist-info/METADATA
reqgen-0.0.11.dist-info/WHEEL
reqgen-0.0.11.dist-info/entry_points.txt
reqgen-0.0.11.dist-info/top_level.txt
reqgen-0.0.11.dist-info/RECORD
