Metadata-Version: 2.1
Name: reqgen
Version: 0.0.11
Summary: ReqGen is a requirements generator that searchs recursively in a given
Home-page: https://github.com/ruiztulio/reqgen
Author: Tulio Ruiz
Author-email: tulio@vauxoo.com
License: ISCL
Keywords: reqgen
Platform: UNKNOWN
Classifier: Development Status :: 2 - Pre-Alpha
Classifier: Intended Audience :: Developers
Classifier: License :: OSI Approved :: ISC License (ISCL)
Classifier: Natural Language :: English
Classifier: Programming Language :: Python :: 2
Classifier: Programming Language :: Python :: 2.7
Classifier: Programming Language :: Python :: 3
Classifier: Programming Language :: Python :: 3.4
Classifier: Programming Language :: Python :: 3.5
Requires-Dist: click (==6.6)
Requires-Dist: requirements-parser (==0.2.0) ; python_version < "3.6"
Requires-Dist: requirements-parser (==0.6.0) ; python_version == "3.6"
Requires-Dist: requirements-parser (==0.7.0) ; python_version == "3.7"
Requires-Dist: requirements-parser (==0.9.0) ; python_version > "3.7"
